{
  "last_updated": "2026-03-17T18:56:41.334026+00:00",
  "items": [
    {
      "title_original": "В Новгороде нашли колодец XII-XIII веков, заполненный обломками посуды",
      "title_neutral": "В Новгороде нашли колодец XII-XIII веков, заполненный обломками посуды",
      "excerpt": "По словам исследователей, колодец какое-то время использовался в качестве помойки",
      "recap_neutral": "По словам исследователей, колодец какое-то время использовался в качестве помойки",
      "main_idea": "В Новгороде нашли колодец XII-XIII веков, заполненный обломками посуды",
      "tags": [],
      "source": "ТАСС",
      "published_at": "Tue, 17 Mar 2026 21:53:23 +0300",
      "url": "https://tass.ru/nauka/26795053",
      "lang": "ru",
      "bias_score": 62,
      "left_right_index": 12,
      "confidence": "heuristic"
    },
    {
      "title_original": "В Петрозаводске в двух районах частично отключили свет",
      "title_neutral": "В Петрозаводске в двух районах частично отключили свет",
      "excerpt": "Отключения произошли из-за аварии",
      "recap_neutral": "Отключения произошли из-за аварии",
      "main_idea": "В Петрозаводске в двух районах частично отключили свет",
      "tags": [
        "tech"
      ],
      "source": "ТАСС",
      "published_at": "Tue, 17 Mar 2026 21:49:28 +0300",
      "url": "https://tass.ru/obschestvo/26795195",
      "lang": "ru",
      "bias_score": 62,
      "left_right_index": 12,
      "confidence": "heuristic"
    },
    {
      "title_original": "В Нидерландах открылся новый сезон одного из крупнейших тюльпановых парков мира",
      "title_neutral": "В Нидерландах открылся новый сезон одного из крупнейших тюльпановых парков мира",
      "excerpt": "Торжественная церемония прошла в павильоне Оранье-Нассау при участии представителей отрасли и международных гостей",
      "recap_neutral": "Торжественная церемония прошла в павильоне Оранье-Нассау при участии представителей отрасли и международных гостей",
      "main_idea": "В Нидерландах открылся новый сезон одного из крупнейших тюльпановых парков мира",
      "tags": [
        "tech"
      ],
      "source": "ТАСС",
      "published_at": "Tue, 17 Mar 2026 21:46:20 +0300",
      "url": "https://tass.ru/kultura/26795067",
      "lang": "ru",
      "bias_score": 62,
      "left_right_index": 12,
      "confidence": "heuristic"
    },
    {
      "title_original": "ЦСКА потерпел свое крупнейшее поражение в Кубке России по футболу",
      "title_neutral": "ЦСКА потерпел свое крупнейшее поражение в Кубке России по футболу",
      "excerpt": "Красно-синие уступили \"Краснодару\" со счетом 0:4",
      "recap_neutral": "Красно-синие уступили \"Краснодару\" со счетом 0:4",
      "main_idea": "ЦСКА потерпел свое крупнейшее поражение в Кубке России по футболу",
      "tags": [
        "tech"
      ],
      "source": "ТАСС",
      "published_at": "Tue, 17 Mar 2026 21:44:45 +0300",
      "url": "https://tass.ru/sport/26795173",
      "lang": "ru",
      "bias_score": 62,
      "left_right_index": 12,
      "confidence": "heuristic"
    },
    {
      "title_original": "В Ярославле шесть человек оштрафовали за запрещенную символику",
      "title_neutral": "В Ярославле шесть человек оштрафовали за запрещенную символику",
      "excerpt": "Фигурантов задержали в ночном клубе на концерте",
      "recap_neutral": "Фигурантов задержали в ночном клубе на концерте",
      "main_idea": "В Ярославле шесть человек оштрафовали за запрещенную символику",
      "tags": [],
      "source": "ТАСС",
      "published_at": "Tue, 17 Mar 2026 21:44:35 +0300",
      "url": "https://tass.ru/proisshestviya/26795175",
      "lang": "ru",
      "bias_score": 62,
      "left_right_index": 12,
      "confidence": "heuristic"
    },
    {
      "title_original": "Ещенко верит, что \"Спартак\" сможет пройти московское \"Динамо\" в Кубке России",
      "title_neutral": "Ещенко верит, что \"Спартак\" сможет пройти московское \"Динамо\" в Кубке России",
      "excerpt": "В первой полуфинальной встрече \"пути РПЛ\" бело-голубые победили со счетом 5:2",
      "recap_neutral": "В первой полуфинальной встрече \"пути РПЛ\" бело-голубые победили со счетом 5:2",
      "main_idea": "Ещенко верит, что \"Спартак\" сможет пройти московское \"Динамо\" в Кубке России",
      "tags": [
        "tech"
      ],
      "source": "ТАСС",
      "published_at": "Tue, 17 Mar 2026 21:44:30 +0300",
      "url": "https://tass.ru/sport/26795183",
      "lang": "ru",
      "bias_score": 62,
      "left_right_index": 12,
      "confidence": "heuristic"
    },
    {
      "title_original": "Премьер-министр Перу Миральес покинула пост",
      "title_neutral": "Премьер-министр Перу Миральес покинула пост",
      "excerpt": "",
      "recap_neutral": "Премьер-министр Перу Миральес покинула пост",
      "main_idea": "Премьер-министр Перу Миральес покинула пост",
      "tags": [],
      "source": "ТАСС",
      "published_at": "Tue, 17 Mar 2026 21:40:04 +0300",
      "url": "https://tass.ru/mezhdunarodnaya-panorama/26795177",
      "lang": "ru",
      "bias_score": 62,
      "left_right_index": 12,
      "confidence": "heuristic"
    },
    {
      "title_original": "Эксперт Мясоедов назвал фейки про Мах попыткой очернения платформы",
      "title_neutral": "Эксперт Мясоедов назвал фейки про Мах попыткой очернения платформы",
      "excerpt": "Такие заявления являются стремлением создать недобросовестную конкуренцию, отметил генеральный директор компании \"ИТ-Резерв\"",
      "recap_neutral": "Такие заявления являются стремлением создать недобросовестную конкуренцию, отметил генеральный директор компании \"ИТ-Резерв\"",
      "main_idea": "Эксперт Мясоедов назвал фейки про Мах попыткой очернения платформы",
      "tags": [
        "tech"
      ],
      "source": "ТАСС",
      "published_at": "Tue, 17 Mar 2026 21:39:32 +0300",
      "url": "https://tass.ru/ekonomika/26795077",
      "lang": "ru",
      "bias_score": 62,
      "left_right_index": 12,
      "confidence": "heuristic"
    },
    {
      "title_original": "КСИР подтвердил гибель главы военизированного ополчения Ирана \"Басидж\"",
      "title_neutral": "КСИР подтвердил гибель главы военизированного ополчения Ирана \"Басидж\"",
      "excerpt": "Речь идет о генерал-майоре Голамрезы Солеймани",
      "recap_neutral": "Речь идет о генерал-майоре Голамрезы Солеймани",
      "main_idea": "КСИР подтвердил гибель главы военизированного ополчения Ирана \"Басидж\"",
      "tags": [],
      "source": "ТАСС",
      "published_at": "Tue, 17 Mar 2026 21:38:19 +0300",
      "url": "https://tass.ru/mezhdunarodnaya-panorama/26795155",
      "lang": "ru",
      "bias_score": 62,
      "left_right_index": 12,
      "confidence": "heuristic"
    },
    {
      "title_original": "Умер патриарх Грузии Илия Второй",
      "title_neutral": "Умер патриарх Грузии Илия Второй",
      "excerpt": "Ему было 93 года",
      "recap_neutral": "Ему было 93 года",
      "main_idea": "Умер патриарх Грузии Илия Второй",
      "tags": [
        "tech"
      ],
      "source": "ТАСС",
      "published_at": "Tue, 17 Mar 2026 21:37:10 +0300",
      "url": "https://tass.ru/obschestvo/26795149",
      "lang": "ru",
      "bias_score": 62,
      "left_right_index": 12,
      "confidence": "heuristic"
    },
    {
      "title_original": "\"Краснодар\" разгромил ЦСКА и вышел в финал \"пути РПЛ\" Кубка России",
      "title_neutral": "\"Краснодар\" разгромил ЦСКА и вышел в финал \"пути РПЛ\" Кубка России",
      "excerpt": "Ответная полуфинальная встреча завершилась победой краснодарской команды со счетом 4:0",
      "recap_neutral": "Ответная полуфинальная встреча завершилась победой краснодарской команды со счетом 4:0",
      "main_idea": "\"Краснодар\" разгромил ЦСКА и вышел в финал \"пути РПЛ\" Кубка России",
      "tags": [
        "tech"
      ],
      "source": "ТАСС",
      "published_at": "Tue, 17 Mar 2026 21:33:53 +0300",
      "url": "https://tass.ru/sport/26795143",
      "lang": "ru",
      "bias_score": 62,
      "left_right_index": 12,
      "confidence": "heuristic"
    },
    {
      "title_original": "Долина подтвердила, что ее концерт в Петербурге состоится",
      "title_neutral": "Долина подтвердила, что ее концерт в Петербурге состоится",
      "excerpt": "Мероприятие пройдет 15 ноября",
      "recap_neutral": "Мероприятие пройдет 15 ноября",
      "main_idea": "Долина подтвердила, что ее концерт в Петербурге состоится",
      "tags": [],
      "source": "ТАСС",
      "published_at": "Tue, 17 Mar 2026 21:33:52 +0300",
      "url": "https://tass.ru/kultura/26795015",
      "lang": "ru",
      "bias_score": 62,
      "left_right_index": 12,
      "confidence": "heuristic"
    },
    {
      "title_original": "Трамп заявил, что мог бы принять решение о выходе из НАТО и без Конгресса",
      "title_neutral": "Трамп заявил, что мог бы принять решение о выходе из НАТО и без Конгресса",
      "excerpt": "При этом президент США сообщил, что не ставит пока вопрос о выходе из альянса",
      "recap_neutral": "При этом президент США сообщил, что не ставит пока вопрос о выходе из альянса",
      "main_idea": "Трамп заявил, что мог бы принять решение о выходе из НАТО и без Конгресса",
      "tags": [
        "politics"
      ],
      "source": "ТАСС",
      "published_at": "Tue, 17 Mar 2026 21:33:14 +0300",
      "url": "https://tass.ru/mezhdunarodnaya-panorama/26795135",
      "lang": "ru",
      "bias_score": 62,
      "left_right_index": 12,
      "confidence": "heuristic"
    },
    {
      "title_original": "Депутат Фомин: нацисты истерили в дни Крымской весны, что Херсонщина будет следующей",
      "title_neutral": "Депутат Фомин: нацисты истерили в дни Крымской весны, что Херсонщина будет следующей",
      "excerpt": "По словам Александра Фомина, для жителей Херсонской области события в Крыму стали \"надеждой на справедливость\"",
      "recap_neutral": "По словам Александра Фомина, для жителей Херсонской области события в Крыму стали \"надеждой на справедливость\"",
      "main_idea": "Депутат Фомин: нацисты истерили в дни Крымской весны, что Херсонщина будет следующей",
      "tags": [],
      "source": "ТАСС",
      "published_at": "Tue, 17 Mar 2026 21:32:13 +0300",
      "url": "https://tass.ru/obschestvo/26794895",
      "lang": "ru",
      "bias_score": 62,
      "left_right_index": 12,
      "confidence": "heuristic"
    },
    {
      "title_original": "Великобритания исключила банкира Белоуса из антироссийского санкционного списка",
      "title_neutral": "Великобритания исключила банкира Белоуса из антироссийского санкционного списка",
      "excerpt": "Это физическое лицо более не подлежит ограничениям, говорится в сообщении управления по осуществлению финансовых санкций в составе Минфина Соединенного Королевства",
      "recap_neutral": "Это физическое лицо более не подлежит ограничениям, говорится в сообщении управления по осуществлению финансовых санкций в составе Минфина Соединенного Королевства",
      "main_idea": "Великобритания исключила банкира Белоуса из антироссийского санкционного списка",
      "tags": [
        "economy",
        "tech"
      ],
      "source": "ТАСС",
      "published_at": "Tue, 17 Mar 2026 21:29:34 +0300",
      "url": "https://tass.ru/mezhdunarodnaya-panorama/26795113",
      "lang": "ru",
      "bias_score": 62,
      "left_right_index": 12,
      "confidence": "heuristic"
    },
    {
      "title_original": "Iran War Live Updates: Israel Says It Has Dealt Blow to Regime by Killing Top Official",
      "title_neutral": "Iran War Live Updates: Israel Says It Has Dealt Blow to Regime by Killing Top Official",
      "excerpt": "Ali Larijani, a security official who has acted as the country’s de facto leader, was killed in an overnight strike, the Israeli military said. In Washington, President Trump said he was not afraid of sending ground troops to Iran.",
      "recap_neutral": "Ali Larijani, a security official who has acted as the country’s de facto leader, was killed in an overnight strike, the Israeli military said",
      "main_idea": "Iran War Live Updates: Israel Says It Has Dealt Blow to Regime by Killing Top Official",
      "tags": [
        "politics",
        "conflict",
        "tech"
      ],
      "source": "NYTimes World",
      "published_at": "Tue, 17 Mar 2026 18:53:39 +0000",
      "url": "https://www.nytimes.com/live/2026/03/17/world/iran-war-trump-oil-lebanon",
      "lang": "en",
      "bias_score": 55,
      "left_right_index": -18,
      "confidence": "heuristic"
    },
    {
      "title_original": "Air strike hit Kabul rehab centre as patients ate dinner, survivor tells BBC",
      "title_neutral": "Air strike hit Kabul rehab centre as patients ate dinner, survivor tells BBC",
      "excerpt": "The exact number killed in Monday night's strike by Pakistan is still not known, but is feared to be in the hundreds.",
      "recap_neutral": "The exact number killed in Monday night's strike by Pakistan is still not known, but is feared to be in the hundreds",
      "main_idea": "Air strike hit Kabul rehab centre as patients ate dinner, survivor tells BBC",
      "tags": [
        "conflict",
        "tech"
      ],
      "source": "BBC World",
      "published_at": "Tue, 17 Mar 2026 18:45:54 GMT",
      "url": "https://www.bbc.com/news/articles/ckg1kgz6wkgo?at_medium=RSS&at_campaign=rss",
      "lang": "en",
      "bias_score": 42,
      "left_right_index": -5,
      "confidence": "heuristic"
    },
    {
      "title_original": "Antisemitic Attacks Bring Deeper Unease to Dutch Jews",
      "title_neutral": "Antisemitic Attacks Bring Deeper Unease to Dutch Jews",
      "excerpt": "Since a school and a synagogue were attacked over two days, an unsettling feeling has spread among Jews in the Netherlands.",
      "recap_neutral": "Since a school and a synagogue were attacked over two days, an unsettling feeling has spread among Jews in the Netherlands",
      "main_idea": "Antisemitic Attacks Bring Deeper Unease to Dutch Jews",
      "tags": [
        "conflict"
      ],
      "source": "NYTimes World",
      "published_at": "Tue, 17 Mar 2026 18:21:21 +0000",
      "url": "https://www.nytimes.com/2026/03/17/world/europe/antisemitism-netherlands-amsterdam-rotterdam.html",
      "lang": "en",
      "bias_score": 55,
      "left_right_index": -18,
      "confidence": "heuristic"
    },
    {
      "title_original": "Illinois Introducing Operating System Account Age Bill",
      "title_neutral": "Illinois Introducing Operating System Account Age Bill",
      "excerpt": "Comments",
      "recap_neutral": "Comments",
      "main_idea": "Illinois Introducing Operating System Account Age Bill",
      "tags": [],
      "source": "Hacker News",
      "published_at": "Tue, 17 Mar 2026 18:06:07 +0000",
      "url": "https://www.ilga.gov/Legislation/BillStatus?DocTypeID=HB&DocNum=5511",
      "lang": "en",
      "bias_score": 46,
      "left_right_index": -4,
      "confidence": "heuristic"
    },
    {
      "title_original": "Belgian court sends ex-diplomat, 93, to trial over 1961 murder of Congo leader",
      "title_neutral": "Belgian court sends ex-diplomat, 93, to trial over 1961 murder of Congo leader",
      "excerpt": "Family of then PM, Patrice Lumumba, welcome decision to charge Étienne Davignon as ‘beginning of a reckoning’ A former Belgian diplomat, 93, should stand trial over alleged complicity in the 1961 murder of Patrice Lumumba, the first prime minister of what was then the newly independent Congolese st…",
      "recap_neutral": "Family of then PM, Patrice Lumumba, welcome decision to charge Étienne Davignon as ‘beginning of a reckoning’ A former Belgian diplomat, 93, should stand trial over alleged complicity in the 1961 murder of Patrice Lumum…",
      "main_idea": "Belgian court sends ex-diplomat, 93, to trial over 1961 murder of Congo leader",
      "tags": [],
      "source": "The Guardian",
      "published_at": "Tue, 17 Mar 2026 18:03:45 GMT",
      "url": "https://www.theguardian.com/world/2026/mar/17/ex-belgian-diplomat-93-trial-1961-murder-patrice-lumumba",
      "lang": "en",
      "bias_score": 60,
      "left_right_index": -28,
      "confidence": "heuristic"
    },
    {
      "title_original": "If you thought the code writing speed was your problem; you have bigger problems",
      "title_neutral": "If you thought the code writing speed was your problem; you have bigger problems",
      "excerpt": "Comments",
      "recap_neutral": "Comments",
      "main_idea": "If you thought the code writing speed was your problem; you have bigger problems",
      "tags": [],
      "source": "Hacker News",
      "published_at": "Tue, 17 Mar 2026 17:48:50 +0000",
      "url": "https://andrewmurphy.io/blog/if-you-thought-the-speed-of-writing-code-was-your-problem-you-have-bigger-problems",
      "lang": "en",
      "bias_score": 46,
      "left_right_index": -4,
      "confidence": "heuristic"
    },
    {
      "title_original": "Dozens Dead in Pakistani Airstrike on Kabul",
      "title_neutral": "Dozens Dead in Pakistani Airstrike on Kabul",
      "excerpt": "The attack hit a drug rehabilitation facility, and Afghanistan vowed to retaliate, risking an escalation of the conflict between the two countries.",
      "recap_neutral": "The attack hit a drug rehabilitation facility, and Afghanistan vowed to retaliate, risking an escalation of the conflict between the two countries",
      "main_idea": "Dozens Dead in Pakistani Airstrike on Kabul",
      "tags": [
        "conflict",
        "tech"
      ],
      "source": "NYTimes World",
      "published_at": "Tue, 17 Mar 2026 17:44:29 +0000",
      "url": "https://www.nytimes.com/2026/03/17/world/asia/afghanistan-pakistan-kabul-hospital.html",
      "lang": "en",
      "bias_score": 55,
      "left_right_index": -18,
      "confidence": "heuristic"
    },
    {
      "title_original": "Spice Data (YC S19) Is Hiring a Product Specialist",
      "title_neutral": "Spice Data (YC S19) Is Hiring a Product Specialist",
      "excerpt": "Comments",
      "recap_neutral": "Comments",
      "main_idea": "Spice Data (YC S19) Is Hiring a Product Specialist",
      "tags": [],
      "source": "Hacker News",
      "published_at": "Tue, 17 Mar 2026 17:00:50 +0000",
      "url": "https://www.ycombinator.com/companies/spice-data/jobs/P0e9MKz-product-specialist-new-grad",
      "lang": "en",
      "bias_score": 46,
      "left_right_index": -4,
      "confidence": "heuristic"
    },
    {
      "title_original": "Top US counterterrorism official resigns over Iran war, urging Trump to 'reverse course'",
      "title_neutral": "Top US counterterrorism official resigns over Iran war, urging Trump to 'reverse course'",
      "excerpt": "National Counterterrorism Center Director Joe Kent says Trump \"started this war due to pressure from Israel and its powerful American lobby\".",
      "recap_neutral": "National Counterterrorism Center Director Joe Kent says Trump \"started this war due to pressure from Israel and its powerful American lobby\"",
      "main_idea": "Top US counterterrorism official resigns over Iran war, urging Trump to 'reverse course'",
      "tags": [
        "conflict"
      ],
      "source": "BBC World",
      "published_at": "Tue, 17 Mar 2026 16:43:34 GMT",
      "url": "https://www.bbc.com/news/articles/cg4g66r3z40o?at_medium=RSS&at_campaign=rss",
      "lang": "en",
      "bias_score": 42,
      "left_right_index": -5,
      "confidence": "heuristic"
    },
    {
      "title_original": "What have US allies and China said about sending ships to the Strait of Hormuz?",
      "title_neutral": "What have US allies and China said about sending ships to the Strait of Hormuz?",
      "excerpt": "US allies have either pushed back or remained cautious on Trump's initial request to send ships to the crucial oil route.",
      "recap_neutral": "US allies have either pushed back or remained cautious on Trump's initial request to send ships to the crucial oil route",
      "main_idea": "What have US allies and China said about sending ships to the Strait of Hormuz?",
      "tags": [
        "tech"
      ],
      "source": "BBC World",
      "published_at": "Tue, 17 Mar 2026 16:35:29 GMT",
      "url": "https://www.bbc.com/news/articles/crm8g938erdo?at_medium=RSS&at_campaign=rss",
      "lang": "en",
      "bias_score": 42,
      "left_right_index": -5,
      "confidence": "heuristic"
    },
    {
      "title_original": "Water supply cut in Moldova after oil spill blamed on Russian strike in Ukraine",
      "title_neutral": "Water supply cut in Moldova after oil spill blamed on Russian strike in Ukraine",
      "excerpt": "Moldova has imposed a 15-day state of alert in the Dniester river basin as a precaution.",
      "recap_neutral": "Moldova has imposed a 15-day state of alert in the Dniester river basin as a precaution",
      "main_idea": "Water supply cut in Moldova after oil spill blamed on Russian strike in Ukraine",
      "tags": [
        "conflict",
        "tech"
      ],
      "source": "BBC World",
      "published_at": "Tue, 17 Mar 2026 16:10:06 GMT",
      "url": "https://www.bbc.com/news/articles/cwy98qnpg1jo?at_medium=RSS&at_campaign=rss",
      "lang": "en",
      "bias_score": 42,
      "left_right_index": -5,
      "confidence": "heuristic"
    },
    {
      "title_original": "'The Secret Agent': Exploring a Vibrant, yet Violent Brazil (2025)",
      "title_neutral": "'The Secret Agent': Exploring a Vibrant, yet Violent Brazil (2025)",
      "excerpt": "Comments",
      "recap_neutral": "Comments",
      "main_idea": "'The Secret Agent': Exploring a Vibrant, yet Violent Brazil (2025)",
      "tags": [],
      "source": "Hacker News",
      "published_at": "Tue, 17 Mar 2026 15:56:09 +0000",
      "url": "https://theasc.com/articles/the-secret-agent-cinematography",
      "lang": "en",
      "bias_score": 46,
      "left_right_index": -4,
      "confidence": "heuristic"
    },
    {
      "title_original": "Market-Aware Agents Need Instant Knowledge Acquisition, Not the Latest Model",
      "title_neutral": "Market-Aware Agents Need Instant Knowledge Acquisition, Not the Latest Model",
      "excerpt": "Market-aware agents don’t need the latest model. They need instant knowledge acquisition: live, verified data. Bright Data provides the infrastructure to turn hallucinating chatbots into real-time analysts.",
      "recap_neutral": "Market-aware agents don’t need the latest model",
      "main_idea": "Market-Aware Agents Need Instant Knowledge Acquisition, Not the Latest Model",
      "tags": [
        "economy",
        "conflict"
      ],
      "source": "HackerNoon",
      "published_at": "Tue, 17 Mar 2026 15:52:40 GMT",
      "url": "https://hackernoon.com/market-aware-agents-need-instant-knowledge-acquisition-not-the-latest-model?source=rss",
      "lang": "en",
      "bias_score": 48,
      "left_right_index": -2,
      "confidence": "heuristic"
    },
    {
      "title_original": "Chile's president begins building border barrier less than week into term",
      "title_neutral": "Chile's president begins building border barrier less than week into term",
      "excerpt": "José Antonio Kast visited the ditch - a few feet wide and deep - on Monday, calling it a \"milestone\".",
      "recap_neutral": "José Antonio Kast visited the ditch - a few feet wide and deep - on Monday, calling it a \"milestone\"",
      "main_idea": "Chile's president begins building border barrier less than week into term",
      "tags": [
        "politics"
      ],
      "source": "BBC World",
      "published_at": "Tue, 17 Mar 2026 15:49:46 GMT",
      "url": "https://www.bbc.com/news/articles/cvg1227k00eo?at_medium=RSS&at_campaign=rss",
      "lang": "en",
      "bias_score": 42,
      "left_right_index": -5,
      "confidence": "heuristic"
    },
    {
      "title_original": "GitGuardian Reports an 81% Surge of AI-Service Leaks as 29M Secrets Hit Public GitHub",
      "title_neutral": "GitGuardian Reports an 81% Surge of AI-Service Leaks as 29M Secrets Hit Public GitHub",
      "excerpt": "GitGuardian releases 5th edition of its “State of Secrets Sprawl” report. Leaked secrets have been growing roughly 1.6× faster than the active developer population. Leak rates in AI-assisted code were roughly double the GitHub-wide baseline.",
      "recap_neutral": "GitGuardian releases 5th edition of its “State of Secrets Sprawl” report",
      "main_idea": "GitGuardian Reports an 81% Surge of AI-Service Leaks as 29M Secrets Hit Public GitHub",
      "tags": [
        "tech"
      ],
      "source": "HackerNoon",
      "published_at": "Tue, 17 Mar 2026 15:48:53 GMT",
      "url": "https://hackernoon.com/gitguardian-reports-an-81percent-surge-of-ai-service-leaks-as-29m-secrets-hit-public-github?source=rss",
      "lang": "en",
      "bias_score": 42,
      "left_right_index": -2,
      "confidence": "heuristic"
    },
    {
      "title_original": "Show HN: Antfly: Distributed, Multimodal Search and Memory and Graphs in Go",
      "title_neutral": "Show HN: Antfly: Distributed, Multimodal Search and Memory and Graphs in Go",
      "excerpt": "Comments",
      "recap_neutral": "Comments",
      "main_idea": "Show HN: Antfly: Distributed, Multimodal Search and Memory and Graphs in Go",
      "tags": [],
      "source": "Hacker News",
      "published_at": "Tue, 17 Mar 2026 15:45:15 +0000",
      "url": "https://github.com/antflydb/antfly",
      "lang": "en",
      "bias_score": 46,
      "left_right_index": -4,
      "confidence": "heuristic"
    },
    {
      "title_original": "Israel says it killed Iranian security chief Ali Larijani in air strike",
      "title_neutral": "Israel says it killed Iranian security chief Ali Larijani in air strike",
      "excerpt": "The deaths of Larijani and the head of the paramilitary Basij force have not been confirmed by Iranian authorities.",
      "recap_neutral": "The deaths of Larijani and the head of the paramilitary Basij force have not been confirmed by Iranian authorities",
      "main_idea": "Israel says it killed Iranian security chief Ali Larijani in air strike",
      "tags": [
        "conflict",
        "tech"
      ],
      "source": "BBC World",
      "published_at": "Tue, 17 Mar 2026 15:31:43 GMT",
      "url": "https://www.bbc.com/news/articles/c24deezq6meo?at_medium=RSS&at_campaign=rss",
      "lang": "en",
      "bias_score": 42,
      "left_right_index": -5,
      "confidence": "heuristic"
    },
    {
      "title_original": "ChangeNOW Launches Private Send to Break Blockchain Address Tracking",
      "title_neutral": "ChangeNOW Launches Private Send to Break Blockchain Address Tracking",
      "excerpt": "Private Send is a feature designed to prevent direct links between sender and recipient addresses on public blockchains. Instead of a direct wallet-to-wallet transfer, funds are routed through ChangeNOW infrastructure before reaching the final address. To the recipient, the transaction appears stan…",
      "recap_neutral": "Private Send is a feature designed to prevent direct links between sender and recipient addresses on public blockchains",
      "main_idea": "ChangeNOW Launches Private Send to Break Blockchain Address Tracking",
      "tags": [
        "tech"
      ],
      "source": "HackerNoon",
      "published_at": "Tue, 17 Mar 2026 15:31:13 GMT",
      "url": "https://hackernoon.com/changenow-launches-private-send-to-break-blockchain-address-tracking?source=rss",
      "lang": "en",
      "bias_score": 48,
      "left_right_index": -2,
      "confidence": "heuristic"
    },
    {
      "title_original": "Aster Chain Launch: Defining a New Era for Onchain Privacy and Transparency",
      "title_neutral": "Aster Chain Launch: Defining a New Era for Onchain Privacy and Transparency",
      "excerpt": "Aster Chain is a privacy-focused trading ecosystem backed by YZi Labs. The Layer 1 blockchain is designed to dismantle the \"transparency trap\" of modern DeFi. It offers institutional-grade privacy and CEX-level performance.",
      "recap_neutral": "Aster Chain is a privacy-focused trading ecosystem backed by YZi Labs",
      "main_idea": "Aster Chain Launch: Defining a New Era for Onchain Privacy and Transparency",
      "tags": [
        "tech"
      ],
      "source": "HackerNoon",
      "published_at": "Tue, 17 Mar 2026 15:19:58 GMT",
      "url": "https://hackernoon.com/aster-chain-launch-defining-a-new-era-for-onchain-privacy-and-transparency?source=rss",
      "lang": "en",
      "bias_score": 48,
      "left_right_index": -2,
      "confidence": "heuristic"
    },
    {
      "title_original": "Microsoft's 'unhackable' Xbox One has been hacked by 'Bliss'",
      "title_neutral": "Microsoft's 'unhackable' Xbox One has been hacked by 'Bliss'",
      "excerpt": "Comments",
      "recap_neutral": "Comments",
      "main_idea": "Microsoft's 'unhackable' Xbox One has been hacked by 'Bliss'",
      "tags": [],
      "source": "Hacker News",
      "published_at": "Tue, 17 Mar 2026 15:16:29 +0000",
      "url": "https://www.tomshardware.com/video-games/console-gaming/microsofts-unhackable-xbox-one-has-been-hacked-by-bliss-the-2013-console-finally-fell-to-voltage-glitching-allowing-the-loading-of-unsigned-code-at-every-level",
      "lang": "en",
      "bias_score": 46,
      "left_right_index": -4,
      "confidence": "heuristic"
    },
    {
      "title_original": "GSR Acquires Autonomous and Architech to Launch Integrated Capital Markets And Treasury Platform",
      "title_neutral": "GSR Acquires Autonomous and Architech to Launch Integrated Capital Markets And Treasury Platform",
      "excerpt": "GSR acquires Autonomous and Architech for $57 million. Deal significantly expands the firm's ability to support tokenized organizations from formation through scale.",
      "recap_neutral": "GSR acquires Autonomous and Architech for $57 million",
      "main_idea": "GSR Acquires Autonomous and Architech to Launch Integrated Capital Markets And Treasury Platform",
      "tags": [
        "economy",
        "tech"
      ],
      "source": "HackerNoon",
      "published_at": "Tue, 17 Mar 2026 15:11:23 GMT",
      "url": "https://hackernoon.com/gsr-acquires-autonomous-and-architech-to-launch-integrated-capital-markets-and-treasury-platform?source=rss",
      "lang": "en",
      "bias_score": 48,
      "left_right_index": -2,
      "confidence": "heuristic"
    },
    {
      "title_original": "What to Know About Ali Larijani, Iran’s Top Security Official",
      "title_neutral": "What to Know About Ali Larijani, Iran’s Top Security Official",
      "excerpt": "One of Ayatollah Ali Khamenei’s closest confidants, Mr. Larijani emerged as the face of the government after Mr. Khamenei was killed.",
      "recap_neutral": "One of Ayatollah Ali Khamenei’s closest confidants, Mr",
      "main_idea": "What to Know About Ali Larijani, Iran’s Top Security Official",
      "tags": [
        "politics"
      ],
      "source": "NYTimes World",
      "published_at": "Tue, 17 Mar 2026 15:09:06 +0000",
      "url": "https://www.nytimes.com/2026/03/17/world/middleeast/who-is-ali-larijani-iran.html",
      "lang": "en",
      "bias_score": 55,
      "left_right_index": -18,
      "confidence": "heuristic"
    },
    {
      "title_original": "Belgian court clears way for trial over 1961 killing of Congo PM Lumumba",
      "title_neutral": "Belgian court clears way for trial over 1961 killing of Congo PM Lumumba",
      "excerpt": "Etienne Davignon, a 93-year-old ex-diplomat, is accused of involvement in the assassination of the independence hero.",
      "recap_neutral": "Etienne Davignon, a 93-year-old ex-diplomat, is accused of involvement in the assassination of the independence hero",
      "main_idea": "Belgian court clears way for trial over 1961 killing of Congo PM Lumumba",
      "tags": [],
      "source": "BBC World",
      "published_at": "Tue, 17 Mar 2026 15:06:47 GMT",
      "url": "https://www.bbc.com/news/articles/czd899vn6e9o?at_medium=RSS&at_campaign=rss",
      "lang": "en",
      "bias_score": 42,
      "left_right_index": -5,
      "confidence": "heuristic"
    },
    {
      "title_original": "As Carney Seeks Canadian Alliances with China, India and Qatar, He Looks Away on Human Rights",
      "title_neutral": "As Carney Seeks Canadian Alliances with China, India and Qatar, He Looks Away on Human Rights",
      "excerpt": "Canada’s prime minister chooses pragmatism in a turbulent world, which means doing business with countries that do not share Canada’s democratic values. Some critics see this as weakness.",
      "recap_neutral": "Canada’s prime minister chooses pragmatism in a turbulent world, which means doing business with countries that do not share Canada’s democratic values",
      "main_idea": "As Carney Seeks Canadian Alliances with China, India and Qatar, He Looks Away on Human Rights",
      "tags": [],
      "source": "NYTimes World",
      "published_at": "Tue, 17 Mar 2026 14:58:50 +0000",
      "url": "https://www.nytimes.com/2026/03/17/world/canada/canada-carney-alliances-human-rights.html",
      "lang": "en",
      "bias_score": 55,
      "left_right_index": -18,
      "confidence": "heuristic"
    },
    {
      "title_original": "FFmpeg 8.1",
      "title_neutral": "FFmpeg 8.1",
      "excerpt": "Comments",
      "recap_neutral": "Comments",
      "main_idea": "FFmpeg 8.1",
      "tags": [],
      "source": "Hacker News",
      "published_at": "Tue, 17 Mar 2026 14:51:57 +0000",
      "url": "https://ffmpeg.org/index.html#pr8.1",
      "lang": "en",
      "bias_score": 46,
      "left_right_index": -4,
      "confidence": "heuristic"
    },
    {
      "title_original": "MEXC Launches Prediction Market with 0-Fee, Low-Latency Trading Experience",
      "title_neutral": "MEXC Launches Prediction Market with 0-Fee, Low-Latency Trading Experience",
      "excerpt": "MEXC has launched a zero-fee prediction market offering millisecond-level trade execution, allowing users to trade on outcomes tied to global events like geopolitics and crypto trends. Integrated within its existing ecosystem, the platform aims to combine real-time probability signals with trading…",
      "recap_neutral": "MEXC has launched a zero-fee prediction market offering millisecond-level trade execution, allowing users to trade on outcomes tied to global events like geopolitics and crypto trends",
      "main_idea": "MEXC Launches Prediction Market with 0-Fee, Low-Latency Trading Experience",
      "tags": [
        "economy",
        "tech"
      ],
      "source": "HackerNoon",
      "published_at": "Tue, 17 Mar 2026 14:46:21 GMT",
      "url": "https://hackernoon.com/mexc-launches-prediction-market-with-0-fee-low-latency-trading-experience?source=rss",
      "lang": "en",
      "bias_score": 48,
      "left_right_index": -2,
      "confidence": "heuristic"
    },
    {
      "title_original": "Trump Signals He May Intervene in Cuba Following Iran and Venezuela",
      "title_neutral": "Trump Signals He May Intervene in Cuba Following Iran and Venezuela",
      "excerpt": "Still at war with Iran and in control in Venezuela, President Trump is signaling that he is about to intervene in another country.",
      "recap_neutral": "Still at war with Iran and in control in Venezuela, President Trump is signaling that he is about to intervene in another country",
      "main_idea": "Trump Signals He May Intervene in Cuba Following Iran and Venezuela",
      "tags": [
        "politics",
        "conflict"
      ],
      "source": "NYTimes World",
      "published_at": "Tue, 17 Mar 2026 14:46:03 +0000",
      "url": "https://www.nytimes.com/2026/03/17/world/americas/trump-cuba-intervention.html",
      "lang": "en",
      "bias_score": 55,
      "left_right_index": -18,
      "confidence": "heuristic"
    },
    {
      "title_original": "Base58 Labs' BASIS 2026 Blueprint Forges a New Standard for BTC, ETH, SOL & PAXG",
      "title_neutral": "Base58 Labs' BASIS 2026 Blueprint Forges a New Standard for BTC, ETH, SOL & PAXG",
      "excerpt": "Base58 Labs unveiled the [BASIS 2026 Technical Blueprint & Infrastructure Roadmap. New roadmap positions BASIS as an institutional-grade digital asset management platform built for macro volatility.",
      "recap_neutral": "Base58 Labs unveiled the [BASIS 2026 Technical Blueprint & Infrastructure Roadmap",
      "main_idea": "Base58 Labs' BASIS 2026 Blueprint Forges a New Standard for BTC, ETH, SOL & PAXG",
      "tags": [
        "tech"
      ],
      "source": "HackerNoon",
      "published_at": "Tue, 17 Mar 2026 14:39:53 GMT",
      "url": "https://hackernoon.com/base58-labs-basis-2026-blueprint-forges-a-new-standard-for-btc-eth-sol-and-paxg?source=rss",
      "lang": "en",
      "bias_score": 48,
      "left_right_index": -2,
      "confidence": "heuristic"
    },
    {
      "title_original": "Node.js needs a virtual file system",
      "title_neutral": "Node.js needs a virtual file system",
      "excerpt": "Comments",
      "recap_neutral": "Comments",
      "main_idea": "Node.js needs a virtual file system",
      "tags": [],
      "source": "Hacker News",
      "published_at": "Tue, 17 Mar 2026 14:28:37 +0000",
      "url": "https://blog.platformatic.dev/why-nodejs-needs-a-virtual-file-system",
      "lang": "en",
      "bias_score": 46,
      "left_right_index": -4,
      "confidence": "heuristic"
    },
    {
      "title_original": "She's won 24 Paralympic medals. But Oksana Masters wants to talk about times she lost",
      "title_neutral": "She's won 24 Paralympic medals. But Oksana Masters wants to talk about times she lost",
      "excerpt": "Oksana Masters leaves Italy with five new para Nordic skiing medals, extending her reign as the most decorated U.S. Winter Paralympian. She competes in summer sports too and is already eyeing LA 2028.",
      "recap_neutral": "Oksana Masters leaves Italy with five new para Nordic skiing medals, extending her reign as the most decorated U",
      "main_idea": "She's won 24 Paralympic medals. But Oksana Masters wants to talk about times she lost",
      "tags": [],
      "source": "NPR",
      "published_at": "Tue, 17 Mar 2026 14:19:20 -0400",
      "url": "https://www.npr.org/2026/03/17/nx-s1-5749163/oksana-masters-2026-winter-paralympics-medals",
      "lang": "en",
      "bias_score": 52,
      "left_right_index": -6,
      "confidence": "heuristic"
    },
    {
      "title_original": "Man and woman charged with murder of Iranian activist in Canada",
      "title_neutral": "Man and woman charged with murder of Iranian activist in Canada",
      "excerpt": "Charges follow discovery of body of Masood Masjoody, who was a critic of the Tehran regime and the exiled shah Two people have been charged with the murder of an Iranian activist in Canada, in a case which has intensified fears over transnational repression of critics of the regime in Tehran. Masoo…",
      "recap_neutral": "Charges follow discovery of body of Masood Masjoody, who was a critic of the Tehran regime and the exiled shah Two people have been charged with the murder of an Iranian activist in Canada, in a case which has intensifi…",
      "main_idea": "Man and woman charged with murder of Iranian activist in Canada",
      "tags": [],
      "source": "The Guardian",
      "published_at": "Tue, 17 Mar 2026 14:05:58 GMT",
      "url": "https://www.theguardian.com/world/2026/mar/17/two-men-court-murder-iranian-activist-canada",
      "lang": "en",
      "bias_score": 60,
      "left_right_index": -28,
      "confidence": "heuristic"
    },
    {
      "title_original": "Aspiring female Zambian politicians were asked for sexual favours, official says",
      "title_neutral": "Aspiring female Zambian politicians were asked for sexual favours, official says",
      "excerpt": "These reports harm attempts to close the wide gender representation gap in Zambia, activists say.",
      "recap_neutral": "These reports harm attempts to close the wide gender representation gap in Zambia, activists say",
      "main_idea": "Aspiring female Zambian politicians were asked for sexual favours, official says",
      "tags": [],
      "source": "BBC World",
      "published_at": "Tue, 17 Mar 2026 13:31:08 GMT",
      "url": "https://www.bbc.com/news/articles/cm28ldvj3jvo?at_medium=RSS&at_campaign=rss",
      "lang": "en",
      "bias_score": 42,
      "left_right_index": -5,
      "confidence": "heuristic"
    },
    {
      "title_original": "US west coast prepares for 'dangerous' heatwave in early spring",
      "title_neutral": "US west coast prepares for 'dangerous' heatwave in early spring",
      "excerpt": "Severe weather is plaguing the US from coast to coast, bringing a mix of extreme heat and bitter cold.",
      "recap_neutral": "Severe weather is plaguing the US from coast to coast, bringing a mix of extreme heat and bitter cold",
      "main_idea": "US west coast prepares for 'dangerous' heatwave in early spring",
      "tags": [
        "climate"
      ],
      "source": "BBC World",
      "published_at": "Tue, 17 Mar 2026 13:26:03 GMT",
      "url": "https://www.bbc.com/news/articles/cwy80zk8d8xo?at_medium=RSS&at_campaign=rss",
      "lang": "en",
      "bias_score": 42,
      "left_right_index": -5,
      "confidence": "heuristic"
    },
    {
      "title_original": "Sucked Into War, Gulf Countries Face the Limits of U.S. Security Guarantees",
      "title_neutral": "Sucked Into War, Gulf Countries Face the Limits of U.S. Security Guarantees",
      "excerpt": "Barraged by Iranian attacks and questioning the value of security ties with the United States, nations in the Gulf have turned to Ukraine, Australia and Italy for help.",
      "recap_neutral": "Barraged by Iranian attacks and questioning the value of security ties with the United States, nations in the Gulf have turned to Ukraine, Australia and Italy for help",
      "main_idea": "Sucked Into War, Gulf Countries Face the Limits of U.S. Security Guarantees",
      "tags": [
        "conflict",
        "tech"
      ],
      "source": "NYTimes World",
      "published_at": "Tue, 17 Mar 2026 13:12:00 +0000",
      "url": "https://www.nytimes.com/2026/03/17/world/middleeast/iran-war-gulf-saudi-arabia-qatar-emirates.html",
      "lang": "en",
      "bias_score": 55,
      "left_right_index": -18,
      "confidence": "heuristic"
    },
    {
      "title_original": "Ukraine strings nets over cities as killer drones turn streets into war zones",
      "title_neutral": "Ukraine strings nets over cities as killer drones turn streets into war zones",
      "excerpt": "In eastern Ukraine, white nylon nets now stretch over roads and city streets, a low-tech defense against deadly FPV drones that dominate the battlefield and threaten civilians near the front line.",
      "recap_neutral": "In eastern Ukraine, white nylon nets now stretch over roads and city streets, a low-tech defense against deadly FPV drones that dominate the battlefield and threaten civilians near the front line",
      "main_idea": "Ukraine strings nets over cities as killer drones turn streets into war zones",
      "tags": [
        "conflict",
        "tech"
      ],
      "source": "NPR",
      "published_at": "Tue, 17 Mar 2026 13:06:44 -0400",
      "url": "https://www.npr.org/2026/03/17/nx-s1-5743446/russia-ukraine-war-nets-drones",
      "lang": "en",
      "bias_score": 52,
      "left_right_index": -6,
      "confidence": "heuristic"
    },
    {
      "title_original": "Peter Thiel Fears the Antichrist Is Coming. In Rome, Some Call His View Heresy.",
      "title_neutral": "Peter Thiel Fears the Antichrist Is Coming. In Rome, Some Call His View Heresy.",
      "excerpt": "The right-wing tech investor is giving lectures near the Catholic church’s administrative heart. Commentators there are rejecting his apocalyptic vision.",
      "recap_neutral": "The right-wing tech investor is giving lectures near the Catholic church’s administrative heart",
      "main_idea": "Peter Thiel Fears the Antichrist Is Coming. In Rome, Some Call His View Heresy.",
      "tags": [
        "tech"
      ],
      "source": "NYTimes World",
      "published_at": "Tue, 17 Mar 2026 12:58:52 +0000",
      "url": "https://www.nytimes.com/2026/03/17/world/europe/peter-thiel-rome-antichrist-catholics.html",
      "lang": "en",
      "bias_score": 55,
      "left_right_index": -18,
      "confidence": "heuristic"
    },
    {
      "title_original": "Sparse evidence for cannabis to treat mental health conditions highlights research gap",
      "title_neutral": "Sparse evidence for cannabis to treat mental health conditions highlights research gap",
      "excerpt": "A new analysis represents the largest effort yet to systematically parse all the data from high-quality clinical trials on cannabis and mental health. The evidence is lacking.",
      "recap_neutral": "A new analysis represents the largest effort yet to systematically parse all the data from high-quality clinical trials on cannabis and mental health",
      "main_idea": "Sparse evidence for cannabis to treat mental health conditions highlights research gap",
      "tags": [
        "health"
      ],
      "source": "NPR",
      "published_at": "Tue, 17 Mar 2026 12:57:21 -0400",
      "url": "https://www.npr.org/2026/03/17/nx-s1-5750489/cannabis-research-mental-health",
      "lang": "en",
      "bias_score": 52,
      "left_right_index": -6,
      "confidence": "heuristic"
    },
    {
      "title_original": "Show HN: March Madness Bracket Challenge for AI Agents Only",
      "title_neutral": "Show HN: March Madness Bracket Challenge for AI Agents Only",
      "excerpt": "Comments",
      "recap_neutral": "Comments",
      "main_idea": "Show HN: March Madness Bracket Challenge for AI Agents Only",
      "tags": [
        "tech"
      ],
      "source": "Hacker News",
      "published_at": "Tue, 17 Mar 2026 12:56:24 +0000",
      "url": "https://www.Bracketmadness.ai",
      "lang": "en",
      "bias_score": 46,
      "left_right_index": -4,
      "confidence": "heuristic"
    },
    {
      "title_original": "Pakistan air strike kills at least 100 at Kabul drug rehab centre",
      "title_neutral": "Pakistan air strike kills at least 100 at Kabul drug rehab centre",
      "excerpt": "Some of the bodies were injured beyond recognition, forensic laboratory sources told the BBC.",
      "recap_neutral": "Some of the bodies were injured beyond recognition, forensic laboratory sources told the BBC",
      "main_idea": "Pakistan air strike kills at least 100 at Kabul drug rehab centre",
      "tags": [
        "conflict",
        "tech"
      ],
      "source": "BBC World",
      "published_at": "Tue, 17 Mar 2026 12:38:49 GMT",
      "url": "https://www.bbc.com/news/articles/c4g8n7e0l40o?at_medium=RSS&at_campaign=rss",
      "lang": "en",
      "bias_score": 42,
      "left_right_index": -5,
      "confidence": "heuristic"
    },
    {
      "title_original": "At Least 23 Killed in Nigeria as Insurgent Attacks Go On Despite U.S. Help",
      "title_neutral": "At Least 23 Killed in Nigeria as Insurgent Attacks Go On Despite U.S. Help",
      "excerpt": "A teaching hospital and two markets in the city of Maiduguri were hit in what a military spokesman said were suicide bombings by Boko Haram.",
      "recap_neutral": "A teaching hospital and two markets in the city of Maiduguri were hit in what a military spokesman said were suicide bombings by Boko Haram",
      "main_idea": "At Least 23 Killed in Nigeria as Insurgent Attacks Go On Despite U.S. Help",
      "tags": [
        "economy",
        "conflict",
        "tech",
        "health"
      ],
      "source": "NYTimes World",
      "published_at": "Tue, 17 Mar 2026 11:45:17 +0000",
      "url": "https://www.nytimes.com/2026/03/17/world/africa/nigeria-suicide-bombings-maiduguri.html",
      "lang": "en",
      "bias_score": 55,
      "left_right_index": -18,
      "confidence": "heuristic"
    },
    {
      "title_original": "At least 23 people killed in suspected suicide attacks in north-eastern Nigeria",
      "title_neutral": "At least 23 people killed in suspected suicide attacks in north-eastern Nigeria",
      "excerpt": "More than 100 others injured in bombings targeting post office, market areas and hospital in Maiduguri At least 23 people have been killed and more than 100 others injured in multiple suspected suicide bombings in the north-eastern Nigerian city of Maiduguri, shattering its reputation as a relative…",
      "recap_neutral": "More than 100 others injured in bombings targeting post office, market areas and hospital in Maiduguri At least 23 people have been killed and more than 100 others injured in multiple suspected suicide bombings in the n…",
      "main_idea": "At least 23 people killed in suspected suicide attacks in north-eastern Nigeria",
      "tags": [
        "economy",
        "conflict",
        "tech",
        "health"
      ],
      "source": "The Guardian",
      "published_at": "Tue, 17 Mar 2026 11:28:01 GMT",
      "url": "https://www.theguardian.com/world/2026/mar/17/bombings-north-eastern-nigeria-maiduguri",
      "lang": "en",
      "bias_score": 60,
      "left_right_index": -28,
      "confidence": "heuristic"
    },
    {
      "title_original": "‘These connections are overlooked’: how British companies profited from slavery in Brazil long after abolition",
      "title_neutral": "‘These connections are overlooked’: how British companies profited from slavery in Brazil long after abolition",
      "excerpt": "Britons learn about the country’s involvement ‘almost as a self-congratulatory narrative’, says historian Joseph Mulhern In 1845 British citizens and companies were already legally prohibited from owning or buying enslaved people overseas, yet that year 385 captives were “transferred” to a British…",
      "recap_neutral": "Britons learn about the country’s involvement ‘almost as a self-congratulatory narrative’, says historian Joseph Mulhern In 1845 British citizens and companies were already legally prohibited from owning or buying ensla…",
      "main_idea": "‘These connections are overlooked’: how British companies profited from slavery in Brazil long after abolition",
      "tags": [],
      "source": "The Guardian",
      "published_at": "Tue, 17 Mar 2026 11:00:44 GMT",
      "url": "https://www.theguardian.com/world/2026/mar/17/connections-overlooked-how-british-companies-profited-slavery-brazil-after-abolition",
      "lang": "en",
      "bias_score": 60,
      "left_right_index": -28,
      "confidence": "heuristic"
    },
    {
      "title_original": "Adobe and NVIDIA Promise to “Reinvent Creativity” — but Mostly in Future Tense",
      "title_neutral": "Adobe and NVIDIA Promise to “Reinvent Creativity” — but Mostly in Future Tense",
      "excerpt": "Adobe and NVIDIA rolled out yet another self-congratulatory “strategic partnership,” promising to “accelerate AI-powered creation, production, and personalization” — corporate speak that translates roughly to: we’re going to spend a lot of money, use a lot of buzzwords, and maybe, someday, deliver…",
      "recap_neutral": "Adobe and NVIDIA rolled out yet another self-congratulatory “strategic partnership,” promising to “accelerate AI-powered creation, production, and personalization” — corporate speak that translates roughly to: we’re goi…",
      "main_idea": "Adobe and NVIDIA Promise to “Reinvent Creativity” — but Mostly in Future Tense",
      "tags": [
        "tech"
      ],
      "source": "HackerNoon",
      "published_at": "Tue, 17 Mar 2026 10:55:33 GMT",
      "url": "https://hackernoon.com/adobe-and-nvidia-promise-to-reinvent-creativity-but-mostly-in-future-tense?source=rss",
      "lang": "en",
      "bias_score": 48,
      "left_right_index": -2,
      "confidence": "heuristic"
    },
    {
      "title_original": "Trump seeks to delay meeting with Xi in China",
      "title_neutral": "Trump seeks to delay meeting with Xi in China",
      "excerpt": "The escalating war in Iran has overshadowed many of the US' foreign policy objectives",
      "recap_neutral": "The escalating war in Iran has overshadowed many of the US' foreign policy objectives",
      "main_idea": "Trump seeks to delay meeting with Xi in China",
      "tags": [
        "conflict"
      ],
      "source": "BBC World",
      "published_at": "Tue, 17 Mar 2026 10:33:49 GMT",
      "url": "https://www.bbc.com/news/articles/cn9e0z7v3nxo?at_medium=RSS&at_campaign=rss",
      "lang": "en",
      "bias_score": 42,
      "left_right_index": -5,
      "confidence": "heuristic"
    },
    {
      "title_original": "The Postal Service may be out of cash in 2027 without Congress' help, postmaster says",
      "title_neutral": "The Postal Service may be out of cash in 2027 without Congress' help, postmaster says",
      "excerpt": "The U.S. Postal Service's leader says it is set to run out of money in less than a year and may have to stop deliveries because of declining mail volume and what USPS sees as burdensome requirements.",
      "recap_neutral": "The U",
      "main_idea": "The Postal Service may be out of cash in 2027 without Congress' help, postmaster says",
      "tags": [
        "tech"
      ],
      "source": "NPR",
      "published_at": "Tue, 17 Mar 2026 10:31:59 -0400",
      "url": "https://www.npr.org/2026/03/17/nx-s1-5750419/usps-running-out-of-money-postal-service-david-steiner",
      "lang": "en",
      "bias_score": 52,
      "left_right_index": -6,
      "confidence": "heuristic"
    },
    {
      "title_original": "Europe Has Helped the U.S. Protect Shipping. The Strait of Hormuz Is Different.",
      "title_neutral": "Europe Has Helped the U.S. Protect Shipping. The Strait of Hormuz Is Different.",
      "excerpt": "European Union ministers and leaders pushed back on ideas to protect the strait, including expanding a maritime operation already in place in the Red Sea.",
      "recap_neutral": "European Union ministers and leaders pushed back on ideas to protect the strait, including expanding a maritime operation already in place in the Red Sea",
      "main_idea": "Europe Has Helped the U.S. Protect Shipping. The Strait of Hormuz Is Different.",
      "tags": [
        "tech"
      ],
      "source": "NYTimes World",
      "published_at": "Tue, 17 Mar 2026 10:29:50 +0000",
      "url": "https://www.nytimes.com/2026/03/17/world/europe/operation-aspides-strait-hormuz.html",
      "lang": "en",
      "bias_score": 55,
      "left_right_index": -18,
      "confidence": "heuristic"
    },
    {
      "title_original": "Joe Kent, a top counterterrorism official, resigns citing Iran war",
      "title_neutral": "Joe Kent, a top counterterrorism official, resigns citing Iran war",
      "excerpt": "Kent said he \"cannot in good conscience\" back the Iran war. In his resignation letter, he says Iran \"posed no imminent threat to our nation.\"",
      "recap_neutral": "Kent said he \"cannot in good conscience\" back the Iran war",
      "main_idea": "Joe Kent, a top counterterrorism official, resigns citing Iran war",
      "tags": [
        "conflict",
        "tech"
      ],
      "source": "NPR",
      "published_at": "Tue, 17 Mar 2026 10:29:26 -0400",
      "url": "https://www.npr.org/2026/03/17/nx-s1-5750426/joe-kent-counterterrorism-official-resigns-trump",
      "lang": "en",
      "bias_score": 52,
      "left_right_index": -6,
      "confidence": "heuristic"
    },
    {
      "title_original": "The 1,000-Pound Sled Pull That Shocked Alaska",
      "title_neutral": "The 1,000-Pound Sled Pull That Shocked Alaska",
      "excerpt": "After John Thornton rescues him, Buck forms his first true bond of love and loyalty with a human. He proves that devotion through incredible feats—attacking a man who assaults Thornton, rescuing him from deadly rapids, and astonishing a crowd by pulling a 1,000-pound sled for 100 yards. Buck’s stre…",
      "recap_neutral": "After John Thornton rescues him, Buck forms his first true bond of love and loyalty with a human",
      "main_idea": "The 1,000-Pound Sled Pull That Shocked Alaska",
      "tags": [
        "conflict"
      ],
      "source": "HackerNoon",
      "published_at": "Tue, 17 Mar 2026 10:15:05 GMT",
      "url": "https://hackernoon.com/the-1000-pound-sled-pull-that-shocked-alaska?source=rss",
      "lang": "en",
      "bias_score": 48,
      "left_right_index": -2,
      "confidence": "heuristic"
    },
    {
      "title_original": "Geopolitics may test the World Cup — a new book draws lessons from the past",
      "title_neutral": "Geopolitics may test the World Cup — a new book draws lessons from the past",
      "excerpt": "Countries all around the world will soon send players to the U.S. to compete in one of soccer's biggest events. Roger Bennett explores how past competitions met cultural and geopolitical moments.",
      "recap_neutral": "Countries all around the world will soon send players to the U",
      "main_idea": "Geopolitics may test the World Cup — a new book draws lessons from the past",
      "tags": [],
      "source": "NPR",
      "published_at": "Tue, 17 Mar 2026 10:02:17 -0400",
      "url": "https://www.npr.org/2026/03/17/nx-s1-5750358/we-are-the-world-cup-book-review",
      "lang": "en",
      "bias_score": 52,
      "left_right_index": -6,
      "confidence": "heuristic"
    },
    {
      "title_original": "AI Agents Are Great at One Thing at a Time. Life Isn't Built That Way.",
      "title_neutral": "AI Agents Are Great at One Thing at a Time. Life Isn't Built That Way.",
      "excerpt": "AI agents excel at individual tasks but struggle to coordinate multiple devices and systems at once. Tethral is building a local-first orchestration layer that interprets natural language intent and dynamically composes coordinated actions across smart home protocols like Zigbee, Matter, and web AP…",
      "recap_neutral": "AI agents excel at individual tasks but struggle to coordinate multiple devices and systems at once",
      "main_idea": "AI Agents Are Great at One Thing at a Time. Life Isn't Built That Way.",
      "tags": [
        "tech"
      ],
      "source": "HackerNoon",
      "published_at": "Tue, 17 Mar 2026 10:00:04 GMT",
      "url": "https://hackernoon.com/ai-agents-are-great-at-one-thing-at-a-time-life-isnt-built-that-way?source=rss",
      "lang": "en",
      "bias_score": 48,
      "left_right_index": -2,
      "confidence": "heuristic"
    },
    {
      "title_original": "Kagi Small Web",
      "title_neutral": "Kagi Small Web",
      "excerpt": "Comments",
      "recap_neutral": "Comments",
      "main_idea": "Kagi Small Web",
      "tags": [],
      "source": "Hacker News",
      "published_at": "Tue, 17 Mar 2026 09:53:53 +0000",
      "url": "https://kagi.com/smallweb/",
      "lang": "en",
      "bias_score": 46,
      "left_right_index": -4,
      "confidence": "heuristic"
    },
    {
      "title_original": "AI Won’t Fix Your Broken IAM Data",
      "title_neutral": "AI Won’t Fix Your Broken IAM Data",
      "excerpt": "Enterprises are rushing to add AI to identity and access management, but fragmented identity data remains a critical weakness. Without a reliable, continuously updated source of identity truth, AI-driven automation can accelerate bad decisions rather than improve security. Experts argue organizatio…",
      "recap_neutral": "Enterprises are rushing to add AI to identity and access management, but fragmented identity data remains a critical weakness",
      "main_idea": "AI Won’t Fix Your Broken IAM Data",
      "tags": [
        "tech"
      ],
      "source": "HackerNoon",
      "published_at": "Tue, 17 Mar 2026 09:45:05 GMT",
      "url": "https://hackernoon.com/ai-wont-fix-your-broken-iam-data?source=rss",
      "lang": "en",
      "bias_score": 48,
      "left_right_index": -2,
      "confidence": "heuristic"
    },
    {
      "title_original": "Trump Says He Will Have the ‘Honor’ of ‘Taking Cuba’",
      "title_neutral": "Trump Says He Will Have the ‘Honor’ of ‘Taking Cuba’",
      "excerpt": "President Trump’s words came amid a nationwide blackout and as a top Cuban official said his country would move to open the economy to foreign investors.",
      "recap_neutral": "President Trump’s words came amid a nationwide blackout and as a top Cuban official said his country would move to open the economy to foreign investors",
      "main_idea": "Trump Says He Will Have the ‘Honor’ of ‘Taking Cuba’",
      "tags": [
        "politics",
        "economy",
        "tech"
      ],
      "source": "NYTimes World",
      "published_at": "Tue, 17 Mar 2026 09:41:06 +0000",
      "url": "https://www.nytimes.com/2026/03/16/world/americas/cuba-us-foreign-investment-businesses.html",
      "lang": "en",
      "bias_score": 55,
      "left_right_index": -18,
      "confidence": "heuristic"
    },
    {
      "title_original": "A Dog on the Edge of Death",
      "title_neutral": "A Dog on the Edge of Death",
      "excerpt": "Buck and the exhausted sled team are sold to inexperienced travelers—Hal, Charles, and Mercedes—whose incompetence and cruelty push the dogs to the brink of death. Starved, beaten, and forced across dangerous thawing ice, Buck finally refuses to move. John Thornton intervenes, saves Buck, and cuts…",
      "recap_neutral": "Buck and the exhausted sled team are sold to inexperienced travelers—Hal, Charles, and Mercedes—whose incompetence and cruelty push the dogs to the brink of death",
      "main_idea": "A Dog on the Edge of Death",
      "tags": [],
      "source": "HackerNoon",
      "published_at": "Tue, 17 Mar 2026 09:00:52 GMT",
      "url": "https://hackernoon.com/a-dog-on-the-edge-of-death?source=rss",
      "lang": "en",
      "bias_score": 48,
      "left_right_index": -2,
      "confidence": "heuristic"
    },
    {
      "title_original": "Why AI Security Must Evolve Into Lifecycle Governance",
      "title_neutral": "Why AI Security Must Evolve Into Lifecycle Governance",
      "excerpt": "As AI becomes embedded in core enterprise systems, cybersecurity must evolve beyond traditional defenses. Researchers argue that organizations need lifecycle governance covering data ingestion, training pipelines, deployment, and runtime monitoring. New threats like model poisoning, prompt injectio…",
      "recap_neutral": "As AI becomes embedded in core enterprise systems, cybersecurity must evolve beyond traditional defenses",
      "main_idea": "Why AI Security Must Evolve Into Lifecycle Governance",
      "tags": [
        "tech"
      ],
      "source": "HackerNoon",
      "published_at": "Tue, 17 Mar 2026 09:00:32 GMT",
      "url": "https://hackernoon.com/why-ai-security-must-evolve-into-lifecycle-governance?source=rss",
      "lang": "en",
      "bias_score": 48,
      "left_right_index": -2,
      "confidence": "heuristic"
    },
    {
      "title_original": "Inside the Supply Line Delivering American Guns to Mexican Cartels",
      "title_neutral": "Inside the Supply Line Delivering American Guns to Mexican Cartels",
      "excerpt": "A surge of weapons is flowing from the U.S. to Mexico. These firearms — sourced from gun shops, shows, websites and apps — are funneled across the border to fuel the country’s most violent crimes.",
      "recap_neutral": "A surge of weapons is flowing from the U",
      "main_idea": "Inside the Supply Line Delivering American Guns to Mexican Cartels",
      "tags": [],
      "source": "NYTimes World",
      "published_at": "Tue, 17 Mar 2026 09:00:18 +0000",
      "url": "https://www.nytimes.com/2026/03/17/world/americas/mexico-us-guns-trafficking-cartels.html",
      "lang": "en",
      "bias_score": 55,
      "left_right_index": -18,
      "confidence": "heuristic"
    },
    {
      "title_original": "U.S. seeks NATO help with Strait of Hormuz. And, federal judge blocks vaccine changes",
      "title_neutral": "U.S. seeks NATO help with Strait of Hormuz. And, federal judge blocks vaccine changes",
      "excerpt": "As the war with Iran intensifies, Trump is demanding that allies help the U.S. reopen the Strait of Hormuz. And, a federal judge halts RFK Jr.'s changes to children's vaccine policies.",
      "recap_neutral": "As the war with Iran intensifies, Trump is demanding that allies help the U",
      "main_idea": "U.S. seeks NATO help with Strait of Hormuz. And, federal judge blocks vaccine changes",
      "tags": [
        "conflict",
        "tech"
      ],
      "source": "NPR",
      "published_at": "Tue, 17 Mar 2026 07:33:03 -0400",
      "url": "https://www.npr.org/2026/03/17/g-s1-114032/up-first-newsletter-iran-israel-lebanon-us-war-cuba-power-outage-rfk-vaccine-protected-status-migrants",
      "lang": "en",
      "bias_score": 52,
      "left_right_index": -6,
      "confidence": "heuristic"
    },
    {
      "title_original": "A Trump official quits over the Iran war, as Israel says it killed 2 Iranian commanders",
      "title_neutral": "A Trump official quits over the Iran war, as Israel says it killed 2 Iranian commanders",
      "excerpt": "Israel says it killed Ali Larijani and Gholamreza Soleimani. Iran has yet to confirm but it would be the highest-profile killings since the targeting of Iran's Ayatollah Ali Khamenei.",
      "recap_neutral": "Israel says it killed Ali Larijani and Gholamreza Soleimani",
      "main_idea": "A Trump official quits over the Iran war, as Israel says it killed 2 Iranian commanders",
      "tags": [
        "conflict"
      ],
      "source": "NPR",
      "published_at": "Tue, 17 Mar 2026 06:47:00 -0400",
      "url": "https://www.npr.org/2026/03/17/nx-s1-5750253/israel-kills-two-top-iranian-commanders",
      "lang": "en",
      "bias_score": 52,
      "left_right_index": -6,
      "confidence": "heuristic"
    },
    {
      "title_original": "Is there a more fair way to sell World Cup tickets?",
      "title_neutral": "Is there a more fair way to sell World Cup tickets?",
      "excerpt": "World Cup tickets are expensive, and buying them has been frustrating and confusing. But this is what economics is for: figuring out the best ways to allocate scarce resources. FIFA, steal these ideas.",
      "recap_neutral": "World Cup tickets are expensive, and buying them has been frustrating and confusing",
      "main_idea": "Is there a more fair way to sell World Cup tickets?",
      "tags": [
        "tech"
      ],
      "source": "NPR",
      "published_at": "Tue, 17 Mar 2026 06:30:00 -0400",
      "url": "https://www.npr.org/sections/planet-money/2026/03/17/g-s1-113996/is-there-a-more-fair-way-to-sell-world-cup-tickets",
      "lang": "en",
      "bias_score": 52,
      "left_right_index": -6,
      "confidence": "heuristic"
    },
    {
      "title_original": "What the Iran War Means for the U.S.-China Relationship",
      "title_neutral": "What the Iran War Means for the U.S.-China Relationship",
      "excerpt": "With the Xi-Trump summit almost certainly delayed, and tensions rising over the war in Iran, vital issues for both the U.S. and China are also being cast into uncertainty.",
      "recap_neutral": "With the Xi-Trump summit almost certainly delayed, and tensions rising over the war in Iran, vital issues for both the U",
      "main_idea": "What the Iran War Means for the U.S.-China Relationship",
      "tags": [
        "conflict",
        "tech"
      ],
      "source": "NYTimes World",
      "published_at": "Tue, 17 Mar 2026 06:18:44 +0000",
      "url": "https://www.nytimes.com/2026/03/17/world/asia/iran-war-china-us-trump-xi.html",
      "lang": "en",
      "bias_score": 55,
      "left_right_index": -18,
      "confidence": "heuristic"
    },
    {
      "title_original": "The TechBeat: Google Antigravity: 20 Game-Changing Prompts for Complete Automation (3/17/2026)",
      "title_neutral": "The TechBeat: Google Antigravity: 20 Game-Changing Prompts for Complete Automation (3/17/2026)",
      "excerpt": "How are you, hacker? 🪐 Want to know what's trending right now?: The Techbeat by HackerNoon has got you covered with fresh content from our trending stories of the day! Set email preference here . ## AI GTM Strategy: Why AEO Is Replacing Traditional Search By @lomitpatel [ 5 Min read ] AI GTM strate…",
      "recap_neutral": "How are you, hacker? 🪐 Want to know what's trending right now?: The Techbeat by HackerNoon has got you covered with fresh content from our trending stories of the day! Set email preference here",
      "main_idea": "The TechBeat: Google Antigravity: 20 Game-Changing Prompts for Complete Automation (3/17/2026)",
      "tags": [
        "tech"
      ],
      "source": "HackerNoon",
      "published_at": "Tue, 17 Mar 2026 06:11:40 GMT",
      "url": "https://hackernoon.com/3-17-2026-techbeat?source=rss",
      "lang": "en",
      "bias_score": 48,
      "left_right_index": -2,
      "confidence": "heuristic"
    },
    {
      "title_original": "I'm concerned about my blood pressure. Can I check it at home?",
      "title_neutral": "I'm concerned about my blood pressure. Can I check it at home?",
      "excerpt": "If you get a high reading at the doctor's office, it may not be definitive. Here's what to know about your risk — and testing your blood pressure at home.",
      "recap_neutral": "If you get a high reading at the doctor's office, it may not be definitive",
      "main_idea": "I'm concerned about my blood pressure. Can I check it at home?",
      "tags": [],
      "source": "NPR",
      "published_at": "Tue, 17 Mar 2026 06:00:00 -0400",
      "url": "https://www.npr.org/2026/03/17/nx-s1-5747421/im-concerned-about-my-blood-pressure-can-i-check-it-at-home",
      "lang": "en",
      "bias_score": 52,
      "left_right_index": -6,
      "confidence": "heuristic"
    },
    {
      "title_original": "And the burger goes to... Michael B Jordan marks Oscars win at In-N-Out",
      "title_neutral": "And the burger goes to... Michael B Jordan marks Oscars win at In-N-Out",
      "excerpt": "Hours after winning best actor, Jordan joins an exclusive list of famous faces to celebrate an Oscar victory with a burger.",
      "recap_neutral": "Hours after winning best actor, Jordan joins an exclusive list of famous faces to celebrate an Oscar victory with a burger",
      "main_idea": "And the burger goes to... Michael B Jordan marks Oscars win at In-N-Out",
      "tags": [],
      "source": "BBC World",
      "published_at": "Tue, 17 Mar 2026 04:41:58 GMT",
      "url": "https://www.bbc.com/news/articles/cpd8w5y0dpdo?at_medium=RSS&at_campaign=rss",
      "lang": "en",
      "bias_score": 42,
      "left_right_index": -5,
      "confidence": "heuristic"
    },
    {
      "title_original": "ZeroSlop: Why I Built the 'SponsorBlock' for AI Slop on X",
      "title_neutral": "ZeroSlop: Why I Built the 'SponsorBlock' for AI Slop on X",
      "excerpt": "Tired of AI-generated \"slop\" ruining your Twitter (X) timeline? ZeroSlop is an open-source, community-powered browser extension that acts like SponsorBlock for AI spam. By using context-aware detection (scanning entire threads or profiles) and a shared Firebase registry, the community can detect, a…",
      "recap_neutral": "Tired of AI-generated \"slop\" ruining your Twitter (X) timeline? ZeroSlop is an open-source, community-powered browser extension that acts like SponsorBlock for AI spam",
      "main_idea": "ZeroSlop: Why I Built the 'SponsorBlock' for AI Slop on X",
      "tags": [
        "conflict",
        "tech"
      ],
      "source": "HackerNoon",
      "published_at": "Tue, 17 Mar 2026 04:41:18 GMT",
      "url": "https://hackernoon.com/zeroslop-why-i-built-the-sponsorblock-for-ai-slop-on-x?source=rss",
      "lang": "en",
      "bias_score": 48,
      "left_right_index": -2,
      "confidence": "heuristic"
    },
    {
      "title_original": "Sri Lanka declares Wednesdays off as Asian countries try to conserve fuel",
      "title_neutral": "Sri Lanka declares Wednesdays off as Asian countries try to conserve fuel",
      "excerpt": "This is the latest in a series of measures undertaken by Asian countries which rely on oil from the Gulf.",
      "recap_neutral": "This is the latest in a series of measures undertaken by Asian countries which rely on oil from the Gulf",
      "main_idea": "Sri Lanka declares Wednesdays off as Asian countries try to conserve fuel",
      "tags": [],
      "source": "BBC World",
      "published_at": "Tue, 17 Mar 2026 04:17:14 GMT",
      "url": "https://www.bbc.com/news/articles/c4g5n58rlnzo?at_medium=RSS&at_campaign=rss",
      "lang": "en",
      "bias_score": 42,
      "left_right_index": -5,
      "confidence": "heuristic"
    },
    {
      "title_original": "As American Bombers Take Off From R.A.F. Fairford in UK, Iraq War Looms Large",
      "title_neutral": "As American Bombers Take Off From R.A.F. Fairford in UK, Iraq War Looms Large",
      "excerpt": "R.A.F. Fairford was the site of repeated antiwar protests during the Iraq war in 2003. Now it is being used again as a base for U.S. bombing missions in the Middle East.",
      "recap_neutral": "R",
      "main_idea": "As American Bombers Take Off From R.A.F. Fairford in UK, Iraq War Looms Large",
      "tags": [
        "conflict",
        "tech"
      ],
      "source": "NYTimes World",
      "published_at": "Tue, 17 Mar 2026 04:01:07 +0000",
      "url": "https://www.nytimes.com/2026/03/17/world/europe/iran-uk-raf-fairford-starmer-trump.html",
      "lang": "en",
      "bias_score": 55,
      "left_right_index": -18,
      "confidence": "heuristic"
    },
    {
      "title_original": "Trump says presidents 'should not have learning disabilities' as he mocks Newsom's dyslexia",
      "title_neutral": "Trump says presidents 'should not have learning disabilities' as he mocks Newsom's dyslexia",
      "excerpt": "The National Center for Learning Disabilities said it was \"disturbed\" by the president's remarks.",
      "recap_neutral": "The National Center for Learning Disabilities said it was \"disturbed\" by the president's remarks",
      "main_idea": "Trump says presidents 'should not have learning disabilities' as he mocks Newsom's dyslexia",
      "tags": [
        "politics",
        "tech"
      ],
      "source": "BBC World",
      "published_at": "Tue, 17 Mar 2026 02:04:48 GMT",
      "url": "https://www.bbc.com/news/articles/c4gjnwmm984o?at_medium=RSS&at_campaign=rss",
      "lang": "en",
      "bias_score": 42,
      "left_right_index": -5,
      "confidence": "heuristic"
    },
    {
      "title_original": "Utah mother who wrote book about grief found guilty of poisoning husband",
      "title_neutral": "Utah mother who wrote book about grief found guilty of poisoning husband",
      "excerpt": "A jury found that Kouri Richins killed her husband in March 2022 by poisoning him with a fentanyl-laced drink.",
      "recap_neutral": "A jury found that Kouri Richins killed her husband in March 2022 by poisoning him with a fentanyl-laced drink",
      "main_idea": "Utah mother who wrote book about grief found guilty of poisoning husband",
      "tags": [],
      "source": "BBC World",
      "published_at": "Tue, 17 Mar 2026 01:14:04 GMT",
      "url": "https://www.bbc.com/news/articles/cdxg1nx2r61o?at_medium=RSS&at_campaign=rss",
      "lang": "en",
      "bias_score": 42,
      "left_right_index": -5,
      "confidence": "heuristic"
    },
    {
      "title_original": "Intrigue, Power Plays and Rivalries: Inside the Rise of Mojtaba Khamenei",
      "title_neutral": "Intrigue, Power Plays and Rivalries: Inside the Rise of Mojtaba Khamenei",
      "excerpt": "The weeklong fight over Iran’s next leader pitted the Revolutionary Guards against moderates. The generals won, but only over spirited resistance.",
      "recap_neutral": "The weeklong fight over Iran’s next leader pitted the Revolutionary Guards against moderates",
      "main_idea": "Intrigue, Power Plays and Rivalries: Inside the Rise of Mojtaba Khamenei",
      "tags": [
        "tech"
      ],
      "source": "NYTimes World",
      "published_at": "Tue, 17 Mar 2026 00:45:26 +0000",
      "url": "https://www.nytimes.com/2026/03/16/world/middleeast/iran-mojtaba-khamenei-election-supreme-leader.html",
      "lang": "en",
      "bias_score": 55,
      "left_right_index": -18,
      "confidence": "heuristic"
    },
    {
      "title_original": "A young girl is knocked over at Tokyo crossing – what’s behind Japan’s ‘bumping’ trend?",
      "title_neutral": "A young girl is knocked over at Tokyo crossing – what’s behind Japan’s ‘bumping’ trend?",
      "excerpt": "Viral video of girl being shoved by fellow pedestrian has reignited debate over butsukari – with experts blaming stress and gender dynamics It starts out as a heartwarming clip. A young girl, clearly delighted to be in Tokyo, beams as she makes a peace sign to the camera. Seconds later, she is shov…",
      "recap_neutral": "Viral video of girl being shoved by fellow pedestrian has reignited debate over butsukari – with experts blaming stress and gender dynamics It starts out as a heartwarming clip",
      "main_idea": "A young girl is knocked over at Tokyo crossing – what’s behind Japan’s ‘bumping’ trend?",
      "tags": [
        "conflict"
      ],
      "source": "The Guardian",
      "published_at": "Thu, 12 Mar 2026 05:00:11 GMT",
      "url": "https://www.theguardian.com/world/2026/mar/12/japan-butsukari-otoko-bumping-man-trend-explained-tokyo-girl-shoved",
      "lang": "en",
      "bias_score": 60,
      "left_right_index": -28,
      "confidence": "heuristic"
    },
    {
      "title_original": "Cory Booker calls both parties ‘feckless’ for ceding war powers to Trump",
      "title_neutral": "Cory Booker calls both parties ‘feckless’ for ceding war powers to Trump",
      "excerpt": "Democrat says Congress ‘doing nothing’ may embolden president to attack countries such as Cuba and North Korea Democratic US senator Cory Booker has criticized both his own political party as well as its Republican counterpart for being “feckless” in ceding congressional war powers to Donald Trump…",
      "recap_neutral": "Democrat says Congress ‘doing nothing’ may embolden president to attack countries such as Cuba and North Korea Democratic US senator Cory Booker has criticized both his own political party as well as its Republican coun…",
      "main_idea": "Cory Booker calls both parties ‘feckless’ for ceding war powers to Trump",
      "tags": [
        "politics",
        "conflict"
      ],
      "source": "The Guardian",
      "published_at": "Sun, 15 Mar 2026 17:00:56 GMT",
      "url": "https://www.theguardian.com/world/2026/mar/15/cory-booker-trump-war-powers-congress",
      "lang": "en",
      "bias_score": 60,
      "left_right_index": -28,
      "confidence": "heuristic"
    },
    {
      "title_original": "Nigeria’s online content creator market has boomed. Can the skit-makers and streamers make it pay?",
      "title_neutral": "Nigeria’s online content creator market has boomed. Can the skit-makers and streamers make it pay?",
      "excerpt": "As platforms make less from advertising, creators are struggling to monetise work – leading to calls for more government investment and tax breaks On a humid afternoon in Lagos, a shoot for a comedy skit is under way on a set that looks more like a small film production. Dozens of people mill about…",
      "recap_neutral": "As platforms make less from advertising, creators are struggling to monetise work – leading to calls for more government investment and tax breaks On a humid afternoon in Lagos, a shoot for a comedy skit is under way on…",
      "main_idea": "Nigeria’s online content creator market has boomed. Can the skit-makers and streamers make it pay?",
      "tags": [
        "politics",
        "economy"
      ],
      "source": "The Guardian",
      "published_at": "Sun, 15 Mar 2026 11:00:23 GMT",
      "url": "https://www.theguardian.com/media/2026/mar/15/nigerias-online-content-creator-market-has-boomed-can-the-skit-makers-and-streamers-make-it-pay",
      "lang": "en",
      "bias_score": 60,
      "left_right_index": -28,
      "confidence": "heuristic"
    },
    {
      "title_original": "Five arrested in Cuba after protest at local Communist party office",
      "title_neutral": "Five arrested in Cuba after protest at local Communist party office",
      "excerpt": "Rare action began peacefully but ‘degenerated into vandalism’ according to state-run newspaper Five people have been arrested in Cuba for acts of “vandalism” after a small group of protesters broke into a provincial office of the Cuban Communist party and set fire to computers and furniture. The in…",
      "recap_neutral": "Rare action began peacefully but ‘degenerated into vandalism’ according to state-run newspaper Five people have been arrested in Cuba for acts of “vandalism” after a small group of protesters broke into a provincial off…",
      "main_idea": "Five arrested in Cuba after protest at local Communist party office",
      "tags": [],
      "source": "The Guardian",
      "published_at": "Sat, 14 Mar 2026 16:42:19 GMT",
      "url": "https://www.theguardian.com/world/2026/mar/14/arrests-cuba-protest-local-communist-party-office",
      "lang": "en",
      "bias_score": 60,
      "left_right_index": -28,
      "confidence": "heuristic"
    },
    {
      "title_original": "Trump seeks to delay China summit as Vance denies ‘wedge’ over Iran war",
      "title_neutral": "Trump seeks to delay China summit as Vance denies ‘wedge’ over Iran war",
      "excerpt": "Pair attempt to strike united front amid reports vice-president skeptical over US-Israeli attack on Iran Donald Trump revealed that he had asked China to delay his forthcoming visit to Beijing while the war with Iran was continuing, as he attempted to strike a united front on Monday with his vice-p…",
      "recap_neutral": "Pair attempt to strike united front amid reports vice-president skeptical over US-Israeli attack on Iran Donald Trump revealed that he had asked China to delay his forthcoming visit to Beijing while the war with Iran wa…",
      "main_idea": "Trump seeks to delay China summit as Vance denies ‘wedge’ over Iran war",
      "tags": [
        "politics",
        "conflict",
        "tech"
      ],
      "source": "The Guardian",
      "published_at": "Mon, 16 Mar 2026 23:52:13 GMT",
      "url": "https://www.theguardian.com/us-news/2026/mar/16/trump-china-summit-iran-war",
      "lang": "en",
      "bias_score": 60,
      "left_right_index": -28,
      "confidence": "heuristic"
    },
    {
      "title_original": "Trump asks China if visit to Beijing can be delayed a month due to Iran war",
      "title_neutral": "Trump asks China if visit to Beijing can be delayed a month due to Iran war",
      "excerpt": "US president had earlier hinted trip could be put on hold if President Xi does not help unblock the strait of Hormuz Middle East crisis – live updates Trump has asked to delay his planned visit to Beijing by about a month due to the Iran war, after earlier hinting he might put the trip off if his p…",
      "recap_neutral": "US president had earlier hinted trip could be put on hold if President Xi does not help unblock the strait of Hormuz Middle East crisis – live updates Trump has asked to delay his planned visit to Beijing by about a mon…",
      "main_idea": "Trump asks China if visit to Beijing can be delayed a month due to Iran war",
      "tags": [
        "politics",
        "conflict",
        "tech"
      ],
      "source": "The Guardian",
      "published_at": "Mon, 16 Mar 2026 22:17:11 GMT",
      "url": "https://www.theguardian.com/world/2026/mar/16/china-us-trump-visit-strait-of-hormuz",
      "lang": "en",
      "bias_score": 60,
      "left_right_index": -28,
      "confidence": "heuristic"
    },
    {
      "title_original": "Cuba’s electrical grid collapses amid US oil blockade",
      "title_neutral": "Cuba’s electrical grid collapses amid US oil blockade",
      "excerpt": "Ten million people left without power in latest of outages that sparked violent protest last weekend Cuba’s national electric grid has collapsed, the country’s grid operator has said, leaving approximately 10 million people without power amid a US-imposed oil blockade that has crippled the island’s…",
      "recap_neutral": "Ten million people left without power in latest of outages that sparked violent protest last weekend Cuba’s national electric grid has collapsed, the country’s grid operator has said, leaving approximately 10 million pe…",
      "main_idea": "Cuba’s electrical grid collapses amid US oil blockade",
      "tags": [
        "tech"
      ],
      "source": "The Guardian",
      "published_at": "Mon, 16 Mar 2026 19:41:29 GMT",
      "url": "https://www.theguardian.com/world/2026/mar/16/cuba-electrical-grid-collapses-amid-us-oil-blockade",
      "lang": "en",
      "bias_score": 60,
      "left_right_index": -28,
      "confidence": "heuristic"
    },
    {
      "title_original": "Give Django your time and money, not your tokens",
      "title_neutral": "Give Django your time and money, not your tokens",
      "excerpt": "Comments",
      "recap_neutral": "Comments",
      "main_idea": "Give Django your time and money, not your tokens",
      "tags": [],
      "source": "Hacker News",
      "published_at": "Mon, 16 Mar 2026 15:12:50 +0000",
      "url": "https://www.better-simple.com/django/2026/03/16/give-django-your-time-and-money/",
      "lang": "en",
      "bias_score": 46,
      "left_right_index": -4,
      "confidence": "heuristic"
    },
    {
      "title_original": "Africa particularly vulnerable as Iran conflict disrupts supply chains, say experts",
      "title_neutral": "Africa particularly vulnerable as Iran conflict disrupts supply chains, say experts",
      "excerpt": "Food production in many African countries depends heavily on fertiliser imported from the Gulf through the strait of Hormuz Countries in Africa, where farmers depend heavily on imported fertiliser and a large share of household income goes on food, are particularly vulnerable to supply chain disrup…",
      "recap_neutral": "Food production in many African countries depends heavily on fertiliser imported from the Gulf through the strait of Hormuz Countries in Africa, where farmers depend heavily on imported fertiliser and a large share of h…",
      "main_idea": "Africa particularly vulnerable as Iran conflict disrupts supply chains, say experts",
      "tags": [
        "conflict",
        "tech"
      ],
      "source": "The Guardian",
      "published_at": "Mon, 16 Mar 2026 12:03:00 GMT",
      "url": "https://www.theguardian.com/world/2026/mar/16/africa-particularly-vulnerable-iran-conflict-disrupts-supply-chains",
      "lang": "en",
      "bias_score": 60,
      "left_right_index": -28,
      "confidence": "heuristic"
    },
    {
      "title_original": "Toward automated verification of unreviewed AI-generated code",
      "title_neutral": "Toward automated verification of unreviewed AI-generated code",
      "excerpt": "Comments",
      "recap_neutral": "Comments",
      "main_idea": "Toward automated verification of unreviewed AI-generated code",
      "tags": [
        "conflict",
        "tech"
      ],
      "source": "Hacker News",
      "published_at": "Mon, 16 Mar 2026 10:52:33 +0000",
      "url": "https://peterlavigne.com/writing/verifying-ai-generated-code",
      "lang": "en",
      "bias_score": 46,
      "left_right_index": -4,
      "confidence": "heuristic"
    },
    {
      "title_original": "Bolivia arrests alleged drug kingpin accused of putting hit on Paraguayan prosecutor",
      "title_neutral": "Bolivia arrests alleged drug kingpin accused of putting hit on Paraguayan prosecutor",
      "excerpt": "Bolivian interior ministry says Sebastián Marset is being extradited to US, where he’s wanted for money laundering Sign up for the Breaking News US email to get newsletter alerts in your inbox Sebastián Marset, an alleged Uruguayan drug trafficker and one of South America’s most wanted criminals, h…",
      "recap_neutral": "Bolivian interior ministry says Sebastián Marset is being extradited to US, where he’s wanted for money laundering Sign up for the Breaking News US email to get newsletter alerts in your inbox Sebastián Marset, an alleg…",
      "main_idea": "Bolivia arrests alleged drug kingpin accused of putting hit on Paraguayan prosecutor",
      "tags": [
        "tech"
      ],
      "source": "The Guardian",
      "published_at": "Fri, 13 Mar 2026 18:37:31 GMT",
      "url": "https://www.theguardian.com/world/2026/mar/13/uruguayan-drug-trafficking-suspect-sebastian-marset-arrested-bolivia",
      "lang": "en",
      "bias_score": 60,
      "left_right_index": -28,
      "confidence": "heuristic"
    },
    {
      "title_original": "Apple cuts China App Store commission fees after government pressure",
      "title_neutral": "Apple cuts China App Store commission fees after government pressure",
      "excerpt": "The move, which lowers fees to 25%, is a breakthrough for Chinese developers Tencent and ByteDance Sign up for the Breaking News US email to get newsletter alerts in your inbox Apple announced late on Thursday it would lower the commission fees collected in its App Store in mainland China . The mov…",
      "recap_neutral": "The move, which lowers fees to 25%, is a breakthrough for Chinese developers Tencent and ByteDance Sign up for the Breaking News US email to get newsletter alerts in your inbox Apple announced late on Thursday it would…",
      "main_idea": "Apple cuts China App Store commission fees after government pressure",
      "tags": [
        "politics",
        "tech"
      ],
      "source": "The Guardian",
      "published_at": "Fri, 13 Mar 2026 16:37:13 GMT",
      "url": "https://www.theguardian.com/technology/2026/mar/13/apple-china-app-store",
      "lang": "en",
      "bias_score": 60,
      "left_right_index": -28,
      "confidence": "heuristic"
    },
    {
      "title_original": "The Plumbing of Everyday Magic",
      "title_neutral": "The Plumbing of Everyday Magic",
      "excerpt": "Comments",
      "recap_neutral": "Comments",
      "main_idea": "The Plumbing of Everyday Magic",
      "tags": [],
      "source": "Hacker News",
      "published_at": "Fri, 13 Mar 2026 15:57:21 +0000",
      "url": "https://plumbing-of-everyday-magic.hyperclay.com/",
      "lang": "en",
      "bias_score": 46,
      "left_right_index": -4,
      "confidence": "heuristic"
    },
    {
      "title_original": "Finding a CPU Design Bug in the Xbox 360 (2018)",
      "title_neutral": "Finding a CPU Design Bug in the Xbox 360 (2018)",
      "excerpt": "Comments",
      "recap_neutral": "Comments",
      "main_idea": "Finding a CPU Design Bug in the Xbox 360 (2018)",
      "tags": [],
      "source": "Hacker News",
      "published_at": "Fri, 13 Mar 2026 13:40:21 +0000",
      "url": "https://randomascii.wordpress.com/2018/01/07/finding-a-cpu-design-bug-in-the-xbox-360/",
      "lang": "en",
      "bias_score": 46,
      "left_right_index": -4,
      "confidence": "heuristic"
    },
    {
      "title_original": "Heart, head, life, fate",
      "title_neutral": "Heart, head, life, fate",
      "excerpt": "Comments",
      "recap_neutral": "Comments",
      "main_idea": "Heart, head, life, fate",
      "tags": [],
      "source": "Hacker News",
      "published_at": "Fri, 13 Mar 2026 03:29:52 +0000",
      "url": "https://www.lrb.co.uk/the-paper/v48/n05/steven-shapin/heart-head-life-fate",
      "lang": "en",
      "bias_score": 46,
      "left_right_index": -4,
      "confidence": "heuristic"
    },
    {
      "title_original": "The kill line v Chinamaxxing: a window into how China and the US see each other",
      "title_neutral": "The kill line v Chinamaxxing: a window into how China and the US see each other",
      "excerpt": "In China, one social media trend hangs on the idea that a life in the US is always one step from disaster, while another in the US has gen Z revelling in Chinese lifestyle hacks Across two online worlds that are normally splintered, over the last few months there has been a mirroring of sorts. On T…",
      "recap_neutral": "In China, one social media trend hangs on the idea that a life in the US is always one step from disaster, while another in the US has gen Z revelling in Chinese lifestyle hacks Across two online worlds that are normall…",
      "main_idea": "The kill line v Chinamaxxing: a window into how China and the US see each other",
      "tags": [],
      "source": "The Guardian",
      "published_at": "Fri, 13 Mar 2026 02:42:20 GMT",
      "url": "https://www.theguardian.com/world/ng-interactive/2026/mar/13/chinamaxxing-social-media-trend-gen-z-china-us",
      "lang": "en",
      "bias_score": 60,
      "left_right_index": -28,
      "confidence": "heuristic"
    }
  ]
}